Aalmond/__init__.py
Aalmond-0.1.0.dist-info/LICENCE.txt
Aalmond-0.1.0.dist-info/METADATA
Aalmond-0.1.0.dist-info/WHEEL
Aalmond-0.1.0.dist-info/top_level.txt
Aalmond-0.1.0.dist-info/RECORD
