Metadata-Version: 2.1
Name: Aalmond
Version: 0.1.0
Summary: Functions for Dataframe Vital Stats, Outliers Detection, Sectional Data View from Mid, Mid Q1, Mid Q3 of a Dataframe
Home-page: UNKNOWN
Author: Manoj S Bhave
Author-email: manojsbhave@gmail.com
License: MIT
Keywords: Data Science,Data Analysis,EDA,Vital Stats,Outliers,Impute,IQR,Zscore,Sectional Dataframe View
Platform: UNKNOWN
Classifier: Development Status :: 5 - Production/Stable
Classifier: Intended Audience :: Education
Classifier: Operating System :: MacOS :: MacOS X
Classifier: Operating System :: Microsoft :: Windows :: Windows 10
Classifier: License :: OSI Approved :: MIT License
Classifier: Programming Language :: Python :: 3
